pandascompare/__init__.py
pandascompare/_data_wrapper.py
pandascompare/compare.py
pandascompare-0.6.1.dist-info/LICENSE
pandascompare-0.6.1.dist-info/METADATA
pandascompare-0.6.1.dist-info/WHEEL
pandascompare-0.6.1.dist-info/RECORD
