Metadata-Version: 2.1
Name: pandascompare
Version: 0.6.1
Summary: Generates comparison reports for pandas DataFrames.
Home-page: https://github.com/zteinck/pandascompare
License: MIT
Author: Zachary Einck
Author-email: zacharyeinck@gmail.com
Requires-Python: >=3.8,<4.0
Classifier: License :: OSI Approved :: MIT License
Classifier: Programming Language :: Python :: 3
Classifier: Programming Language :: Python :: 3.8
Classifier: Programming Language :: Python :: 3.9
Classifier: Programming Language :: Python :: 3.10
Classifier: Programming Language :: Python :: 3.11
Classifier: Programming Language :: Python :: 3.12
Requires-Dist: numpy
Requires-Dist: oddments (>=0.3.1)
Requires-Dist: pandas
Requires-Dist: pathpilot (>=0.3.1)
Project-URL: Repository, https://github.com/zteinck/pandascompare
